[
    {
      "text": "TEST CMS",
      "type": "h1"
    },
    {
      "text": "Chapter 1",
      "type": "h1"
    },
    {
      "text": "Text",
      "type": "h2"
    },
    {
      "text": "vitae elementum velit urna id mi. Sed sodales arcu mi, eu condimentum tellus ornare non. Aliquam non mauris purus. Cras a dignissim tellus. Cras pharetra, felis et convallis tristique, sapien augue interdum ipsum, aliquet rhoncus enim diam vitae eros. Cras ullamcorper, lectus id commodo volutpat, odio urna venenatis tellus, vitae vehicula sapien velit eu purus. Pellentesque a feugiat ex. Proin volutpat congue libero vitae malesuada.",
      "type": "p"
    },
    {
      "text": "Video",
      "type": "h2"
    },
    {
      "text": "https://www.dropbox.com/s/x27pjtymyvoi05f/test.mov?dl=0",
      "type": "link"
    },
    {
      "text": "Audio",
      "type": "h2"
    },
    {
      "text": "https://www.dropbox.com/s/8wcp2h0i3xq3g85/test_audio.m4a?dl=0",
      "type": "link"
    },
    {
      "text": "Chapter 2",
      "type": "h1"
    },
    {
      "text": "Text",
      "type": "h2"
    },
    {
      "text": "vitae elementum velit urna id mi. Sed sodales arcu mi, eu condimentum tellus ornare non. Aliquam non mauris purus. Cras a dignissim tellus. Cras pharetra, felis et convallis tristique, sapien augue interdum ipsum, aliquet rhoncus enim diam vitae eros. Cras ullamcorper, lectus id commodo volutpat, odio urna venenatis tellus, vitae vehicula sapien velit eu purus. Pellentesque a feugiat ex. Proin volutpat congue libero vitae malesuada.",
      "type": "p"
    },
    {
      "text": "Video",
      "type": "h2"
    },
    {
      "text": "https://www.dropbox.com/s/x27pjtymyvoi05f/test.mov?dl=0",
      "type": "link"
    },
    {
      "text": "Audio",
      "type": "h2"
    },
    {
      "text": "https://www.dropbox.com/s/8wcp2h0i3xq3g85/test_audio.m4a?dl=0",
      "type": "link"
    }
  ]